panel_mosaic/__init__.py
panel_mosaic/panel_mosaic.py
panel_mosaic-0.1.0.dist-info/METADATA
panel_mosaic-0.1.0.dist-info/WHEEL
panel_mosaic-0.1.0.dist-info/licenses/LICENSE
panel_mosaic-0.1.0.dist-info/RECORD
